iceportal/__init__.py
iceportal/exceptions.py
iceportal-1.2.0.dist-info/LICENSE
iceportal-1.2.0.dist-info/METADATA
iceportal-1.2.0.dist-info/WHEEL
iceportal-1.2.0.dist-info/RECORD
