Metadata-Version: 2.1
Name: iceportal
Version: 1.2.0
Summary: Python client for getting data from the ICE Portal
License: MIT
Author: Fabian Affolter
Author-email: mail@fabian-affolter.ch
Requires-Python: >=3.11,<4.0
Classifier: License :: OSI Approved :: MIT License
Classifier: Programming Language :: Python :: 3
Classifier: Programming Language :: Python :: 3.11
Classifier: Programming Language :: Python :: 3.12
Requires-Dist: httpx (>=0.24,<1)
